xtdbase/__init__.py
xtdbase/cfg.py
xtdbase/excel.py
xtdbase/mysql.py
xtdbase/mysqlpool.py
xtdbase/redis_client.py
xtdbase/syncmysqlpool.py
xtdbase/untilsql.py
xtdbase-0.1.0.dist-info/licenses/LICENSE
xtdbase-0.1.0.dist-info/METADATA
xtdbase-0.1.0.dist-info/WHEEL
xtdbase-0.1.0.dist-info/top_level.txt
xtdbase-0.1.0.dist-info/RECORD
