Metadata-Version: 2.4
Name: xtdbase
Version: 0.1.0
Summary: 扩展数据库与数据处理工具库 - 提供Excel操作、MySQL连接池、Redis客户端等统一接口
Author-email: sandorn <sandorn@live.cn>
License-Expression: MIT
Project-URL: homepage, https://github.com/sandorn/xtdbase
Project-URL: repository, https://github.com/sandorn/xtdbase
Project-URL: documentation, https://github.com/sandorn/xtdbase/wiki
Project-URL: issues, https://github.com/sandorn/xtdbase/issues
Classifier: Development Status :: 4 - Beta
Classifier: Intended Audience :: Developers
Classifier: Programming Language :: Python :: 3
Classifier: Programming Language :: Python :: 3.13
Classifier: Programming Language :: Python :: 3.14
Classifier: Topic :: Software Development :: Libraries :: Python Modules
Classifier: Topic :: Database
Classifier: Topic :: Office/Business
Classifier: Operating System :: OS Independent
Requires-Python: >=3.13
License-File: LICENSE
Requires-Dist: numpy>=2.3.4
Requires-Dist: openpyxl>=3.1.5
Requires-Dist: pandas>=2.3.3
Requires-Dist: pydantic>=2.12.3
Requires-Dist: xtlog>=0.1.9
Provides-Extra: mysql
Requires-Dist: aiomysql>=0.2.0; extra == "mysql"
Requires-Dist: pymysql>=1.1.2; extra == "mysql"
Requires-Dist: sqlalchemy>=2.0.0; extra == "mysql"
Provides-Extra: redis
Requires-Dist: redis>=6.4.0; extra == "redis"
Provides-Extra: crypto
Requires-Dist: cryptography>=44.0.0; extra == "crypto"
Provides-Extra: all
Requires-Dist: aiomysql>=0.2.0; extra == "all"
Requires-Dist: pymysql>=1.1.2; extra == "all"
Requires-Dist: sqlalchemy>=2.0.0; extra == "all"
Requires-Dist: redis>=6.4.0; extra == "all"
Requires-Dist: cryptography>=44.0.0; extra == "all"
Provides-Extra: test
Requires-Dist: pytest>=7.0.0; extra == "test"
Requires-Dist: pytest-asyncio>=0.21.0; extra == "test"
Dynamic: license-file
